turbodif/__about__.py
turbodif/__init__.py
turbodif-1.0.0.dist-info/LICENSE
turbodif-1.0.0.dist-info/METADATA
turbodif-1.0.0.dist-info/WHEEL
turbodif-1.0.0.dist-info/top_level.txt
turbodif-1.0.0.dist-info/RECORD
