Metadata-Version: 2.1
Name: turbodif
Version: 1.0.0
Summary: Turbonomic Data-Ingestion-Framework library
Home-page: https://github.com/turbonomic/turbodif
Author: Turbonomic
Author-email: ray.mileo@turbonomic.com
License: Apache 2.0
Platform: UNKNOWN
Classifier: Intended Audience :: Developers
Classifier: License :: OSI Approved :: Apache Software License
Classifier: Operating System :: OS Independent
Classifier: Programming Language :: Python :: 3
Classifier: Topic :: Software Development
Requires-Python: >=3.6
